LICENSE
MANIFEST.in
README.rst
requirements.pip
setup.cfg
setup.py
telemetry_email_alerter/__init__.py
telemetry_email_alerter/__main__.py
telemetry_email_alerter.egg-info/PKG-INFO
telemetry_email_alerter.egg-info/SOURCES.txt
telemetry_email_alerter.egg-info/dependency_links.txt
telemetry_email_alerter.egg-info/entry_points.txt
telemetry_email_alerter.egg-info/requires.txt
telemetry_email_alerter.egg-info/top_level.txt