Metadata-Version: 1.1
Name: telemetry_email_alerter
Version: 1.0.6
Summary: Script for subscribing to Arista Telemetry Events and sending email alerts.
Home-page: https://github.com/aristanetworks/telemetry-email-alerter
Author: Arista Telemetry Team
Author-email: telemetry-dev@arista.com
License: UNKNOWN
Download-URL: https://github.com/aristanetworks/telemetry-email-alerter/archive/v1.0.6.tar.gz
Keywords: alerts arista cvp email notifications smtp telemetry
Platform: UNKNOWN
Classifier: Development Status :: 3 - Alpha
Classifier: License :: OSI Approved :: MIT License
Classifier: Programming Language :: Python :: 2.7
